stockbot/__init__.py
stockbot/core.py
stockbot/marketdata.py
stockbot/portfolio.py
stockbot/sources.py
stockbot-0.2.0.dist-info/DESCRIPTION.rst
stockbot-0.2.0.dist-info/METADATA
stockbot-0.2.0.dist-info/RECORD
stockbot-0.2.0.dist-info/WHEEL
stockbot-0.2.0.dist-info/metadata.json
stockbot-0.2.0.dist-info/top_level.txt
