Metadata-Version: 2.0
Name: stockbot
Version: 0.2.0
Summary: Stock market analysis library written in Python.
Home-page: https://github.com/ChrisPappalardo/stockbot
Author: Chris Pappalardo
Author-email: cpappala@yahoo.com
License: CC BY-NC-ND 4.0
Keywords: stockbot
Platform: UNKNOWN
Classifier: Development Status :: 2 - Pre-Alpha
Classifier: Intended Audience :: Developers
Classifier: License :: Other/Proprietary License
Classifier: Natural Language :: English
Classifier: Programming Language :: Python :: 2
Classifier: Programming Language :: Python :: 2.7
Classifier: Programming Language :: Python :: 3
Classifier: Programming Language :: Python :: 3.4
Requires-Dist: TA-lib
Requires-Dist: beautifulsoup4
Requires-Dist: mock
Requires-Dist: numpy
Requires-Dist: pandas
Requires-Dist: python-dateutil
Requires-Dist: pytz
Requires-Dist: requests
Requires-Dist: six
Requires-Dist: zipline
